promptrace/__init__.py
promptrace/config.py
promptrace/core.py
promptrace/enums.py
promptrace/eval.py
promptrace/experiment.py
promptrace/model.py
promptrace/prompt.py
promptrace/tracer.py
promptrace-0.1.3.dist-info/LICENSE
promptrace-0.1.3.dist-info/METADATA
promptrace-0.1.3.dist-info/WHEEL
promptrace-0.1.3.dist-info/top_level.txt
promptrace-0.1.3.dist-info/RECORD
