Metadata-Version: 2.2
Name: promptrace
Version: 0.1.3
Summary: A tool for prompt experimentation and collaboration without additional cloud service.
Author-email: Raihan Alam <raihan.alam@gmail.com>
License: MIT License
Project-URL: Homepage, https://github.com/promptrace/promptrace
Project-URL: Issues, https://github.com/promptrace/promptrace/issues
Classifier: Programming Language :: Python :: 3
Classifier: License :: OSI Approved :: MIT License
Classifier: Operating System :: OS Independent
Requires-Python: >=3.8
License-File: LICENSE
Requires-Dist: pydantic>=2.0.0
Requires-Dist: requests>=2.25.0
Requires-Dist: openai>=1.60.0
